join/__init__.py
join/api.py
join/base.py
join/cache.py
tests/__init__.py
tests/test_join.py
db_join-0.1.8.dist-info/LICENSE
db_join-0.1.8.dist-info/METADATA
db_join-0.1.8.dist-info/WHEEL
db_join-0.1.8.dist-info/top_level.txt
db_join-0.1.8.dist-info/RECORD
