Metadata-Version: 2.1
Name: db-join
Version: 0.1.8
Summary: NoSQL db join
Home-page: https://github.com/freywaid/db-join
Author: Frey Waid
Author-email: logophage1@gmail.com
License: MIT license
Platform: UNKNOWN
Classifier: Programming Language :: Python :: 3
Classifier: License :: OSI Approved :: MIT License
Classifier: Operating System :: OS Independent
Requires-Python: >=3.6
License-File: LICENSE
Requires-Dist: dotted-notation (>=0.6.0)
